<?xml version="1.0" encoding="utf-8" ?><dwsync><file name="Nelson_130625_032_tk_ar_4x6.jpg" server="jupiterupload.vcu.edu//www/www.facilitiesmanagement.vcu.edu/html/" local="3538674493" remote="3538674493" Dst="-1" /><file name="PAYNE_B_4x6.jpg" server="jupiterupload.vcu.edu//www/www.facilitiesmanagement.vcu.edu/html/" local="3544695729" remote="3544695729" Dst="-1" /><file name="TAYLOR_4x6.jpg" server="jupiterupload.vcu.edu//www/www.facilitiesmanagement.vcu.edu/html/" local="3538674488" remote="3538674488" Dst="-1" /><file name="SUTHERLAND_4x6.jpg" server="jupiterupload.vcu.edu//www/www.facilitiesmanagement.vcu.edu/html/" local="3538674491" remote="3538674491" Dst="-1" /><file name="Reardon_130712_010_tk_ar_4x6.jpg" server="jupiterupload.vcu.edu//www/www.facilitiesmanagement.vcu.edu/html/" local="3538674492" remote="3538674492" Dst="-1" /><file name="Dixon.jpg" server="jupiterupload.vcu.edu//www/www.facilitiesmanagement.vcu.edu/html/" local="3558714144" remote="3558714144" Dst="-1" /><file name="Goodwin_130620_088_tk_ar_4x6.jpg" server="jupiterupload.vcu.edu//www/www.facilitiesmanagement.vcu.edu/html/" local="3538674494" remote="3538674494" Dst="-1" /><file name="Fore_130625_101_tk_ar_4x6.jpg" server="jupiterupload.vcu.edu//www/www.facilitiesmanagement.vcu.edu/html/" local="3538674495" remote="3538674495" Dst="-1" /><file name="Sylvia_130712_055_tk_ar_4x6.jpg" server="jupiterupload.vcu.edu//www/www.facilitiesmanagement.vcu.edu/html/" local="3538674492" remote="3538674492" Dst="-1" /><file name="Sullivan.jpg" server="jupiterupload.vcu.edu//www/www.facilitiesmanagement.vcu.edu/html/" local="3558714167" remote="3558714167" Dst="-1" /><file name="Conigliaro_4x6.jpg" server="jupiterupload.vcu.edu//www/www.facilitiesmanagement.vcu.edu/html/" local="3538674487" remote="3538674487" Dst="-1" /><file name="ADAMS_4x6.jpg" server="jupiterupload.vcu.edu//www/www.facilitiesmanagement.vcu.edu/html/" local="3538674490" remote="3538674490" Dst="-1" /><file name="Kraines_130620_062_tk_ar_4x6.jpg" server="jupiterupload.vcu.edu//www/www.facilitiesmanagement.vcu.edu/html/" local="3538674493" remote="3538674493" Dst="-1" /><file name="Zumbrunn_130625_155_tk_ar_4x6.jpg" server="jupiterupload.vcu.edu//www/www.facilitiesmanagement.vcu.edu/html/" local="3538674492" remote="3538674492" Dst="-1" /><file name="KELLAND_4x6.jpg" server="jupiterupload.vcu.edu//www/www.facilitiesmanagement.vcu.edu/html/" local="3538674489" remote="3538674489" Dst="-1" /><file name="JACUBEC_4x6.jpg" server="jupiterupload.vcu.edu//www/www.facilitiesmanagement.vcu.edu/html/" local="3538674490" remote="3538674490" Dst="-1" /><file name="PRICE_4x6.jpg" server="jupiterupload.vcu.edu//www/www.facilitiesmanagement.vcu.edu/html/" local="3538674490" remote="3538674490" Dst="-1" /><file name="BOWER_4x6.jpg" server="jupiterupload.vcu.edu//www/www.facilitiesmanagement.vcu.edu/html/" local="3538674491" remote="3538674491" Dst="-1" /><file name="Maroney_130620_046_tk_ar_4x6.jpg" server="jupiterupload.vcu.edu//www/www.facilitiesmanagement.vcu.edu/html/" local="3538674493" remote="3538674493" Dst="-1" /><file name="Wyatt_130625_116_tk_ar_4x6.jpg" server="jupiterupload.vcu.edu//www/www.facilitiesmanagement.vcu.edu/html/" local="3538674491" remote="3538674491" Dst="-1" /><file name="Karabiac.jpg" server="jupiterupload.vcu.edu//www/www.facilitiesmanagement.vcu.edu/html/" local="3558714155" remote="3558714155" Dst="-1" /><file name="Styles_130712_168_tk_ar_4x6.jpg" server="jupiterupload.vcu.edu//www/www.facilitiesmanagement.vcu.edu/html/" local="3538674492" remote="3538674492" Dst="-1" /><file name="KHayes.jpg" server="jupiterupload.vcu.edu//www/www.facilitiesmanagement.vcu.edu/html/" local="3558716373" remote="3558716373" Dst="-1" /><file name="Guiliani_4x6.jpg" server="jupiterupload.vcu.edu//www/www.facilitiesmanagement.vcu.edu/html/" local="3538674488" remote="3538674488" Dst="-1" /><file name="Hinant_130620_112_tk_ar_4x6.jpg" server="jupiterupload.vcu.edu//www/www.facilitiesmanagement.vcu.edu/html/" local="3538674494" remote="3538674494" Dst="-1" /><file name="larry_small.jpg" server="jupiterupload.vcu.edu//www/www.facilitiesmanagement.vcu.edu/html/" local="3581421010" remote="3581421010" Dst="-1" /><file name="staff.html" server="jupiterupload.vcu.edu//www/www.facilitiesmanagement.vcu.edu/html/" local="3558711226" remote="3558711226" Dst="-1" /><file name="Wellons_130712_050_tk_ar_4x6.jpg" server="jupiterupload.vcu.edu//www/www.facilitiesmanagement.vcu.edu/html/" local="3538674492" remote="3538674492" Dst="-1" /><file name="Mangum_130625_023_tk_ar_4x6.jpg" server="jupiterupload.vcu.edu//www/www.facilitiesmanagement.vcu.edu/html/" local="3538674493" remote="3538674493" Dst="-1" /><file name="Lee_130712_142_tk_ar_4x6.jpg" server="jupiterupload.vcu.edu//www/www.facilitiesmanagement.vcu.edu/html/" local="3570108624" remote="3570108624" Dst="-1" /><file name="STANFORTH_4x6.jpg" server="jupiterupload.vcu.edu//www/www.facilitiesmanagement.vcu.edu/html/" local="3538674488" remote="3538674488" Dst="-1" /><file name="Razo_130620_104_tk_ar_4x6.jpg" server="jupiterupload.vcu.edu//www/www.facilitiesmanagement.vcu.edu/html/" local="3538674492" remote="3538674492" Dst="-1" /><file name="Johnson_130625_133_tk_ar_4x6.jpg" server="jupiterupload.vcu.edu//www/www.facilitiesmanagement.vcu.edu/html/" local="3538674494" remote="3538674494" Dst="-1" /><file name="BECKELHEIMER_4x6.jpg" server="jupiterupload.vcu.edu//www/www.facilitiesmanagement.vcu.edu/html/" local="3538674490" remote="3538674490" Dst="-1" /><file name="Dixon_jr_ar_4x6.jpg" server="jupiterupload.vcu.edu//www/www.facilitiesmanagement.vcu.edu/html/" local="3558612660" remote="3558612660" Dst="-1" /><file name="Taylor_R_4x6.jpg" server="jupiterupload.vcu.edu//www/www.facilitiesmanagement.vcu.edu/html/" local="3544695729" remote="3544695729" Dst="-1" /><file name="Davis_130712_072_tk_ar_4x6.jpg" server="jupiterupload.vcu.edu//www/www.facilitiesmanagement.vcu.edu/html/" local="3538674495" remote="3538674495" Dst="-1" /><file name="HEINITZ_4x6.jpg" server="jupiterupload.vcu.edu//www/www.facilitiesmanagement.vcu.edu/html/" local="3538674490" remote="3538674490" Dst="-1" /><file name="HALL_4x6.jpg" server="jupiterupload.vcu.edu//www/www.facilitiesmanagement.vcu.edu/html/" local="3538674489" remote="3538674489" Dst="-1" /><file name="DeJarnette_130625_145_tk_ar_4x6.jpg" server="jupiterupload.vcu.edu//www/www.facilitiesmanagement.vcu.edu/html/" local="3538674495" remote="3538674495" Dst="-1" /><file name="SaherRandhawa4x6.jpg" server="jupiterupload.vcu.edu//www/www.facilitiesmanagement.vcu.edu/html/" local="3544695729" remote="3544695729" Dst="-1" /><file name="Hartless_130625_118_tk_ar_4x6.jpg" server="jupiterupload.vcu.edu//www/www.facilitiesmanagement.vcu.edu/html/" local="3538674494" remote="3538674494" Dst="-1" /><file name="Powell_130625_044_tk_ar_4x6.jpg" server="jupiterupload.vcu.edu//www/www.facilitiesmanagement.vcu.edu/html/" local="3538674493" remote="3538674493" Dst="-1" /><file name="Payne_130620_032_tk_ar_4x6.jpg" server="jupiterupload.vcu.edu//www/www.facilitiesmanagement.vcu.edu/html/" local="3538674493" remote="3538674493" Dst="-1" /><file name="Britt_130625_067_tk_ar_4x6.jpg" server="jupiterupload.vcu.edu//www/www.facilitiesmanagement.vcu.edu/html/" local="3538674495" remote="3538674495" Dst="-1" /><file name="GIBSON_4x6.jpg" server="jupiterupload.vcu.edu//www/www.facilitiesmanagement.vcu.edu/html/" local="3538674489" remote="3538674489" Dst="-1" /><file name="Thrift_130712_126_tk_ar_4x6.jpg" server="jupiterupload.vcu.edu//www/www.facilitiesmanagement.vcu.edu/html/" local="3538674492" remote="3538674492" Dst="-1" /><file name="Slutzah_130712_087_tk_ar_4x6.jpg" server="jupiterupload.vcu.edu//www/www.facilitiesmanagement.vcu.edu/html/" local="3538674488" remote="3538674488" Dst="-1" /><file name="SCHNIZLER_4x6.jpg" server="jupiterupload.vcu.edu//www/www.facilitiesmanagement.vcu.edu/html/" local="3538674491" remote="3538674491" Dst="-1" /><file name="Karabiac_jr_ar_4x6.jpg" server="jupiterupload.vcu.edu//www/www.facilitiesmanagement.vcu.edu/html/" local="3557486861" remote="3557486861" Dst="-1" /><file name="Gonzales_130712_040_tk_ar_4x6.jpg" server="jupiterupload.vcu.edu//www/www.facilitiesmanagement.vcu.edu/html/" local="3538674494" remote="3538674494" Dst="-1" /><file name="Keland_130625_090_tk_ar_4x6.jpg" server="jupiterupload.vcu.edu//www/www.facilitiesmanagement.vcu.edu/html/" local="3538674494" remote="3538674494" Dst="-1" /><file name="RiChard_4x6.jpg" server="jupiterupload.vcu.edu//www/www.facilitiesmanagement.vcu.edu/html/" local="3538674491" remote="3538674491" Dst="-1" /><file name="sliwoski.jpg" server="jupiterupload.vcu.edu//www/www.facilitiesmanagement.vcu.edu/html/" local="3558712248" remote="3558712248" Dst="-1" /><file name="Helton_130625_116_tk_ar_4x6.jpg" server="jupiterupload.vcu.edu//www/www.facilitiesmanagement.vcu.edu/html/" local="3538674491" remote="3538674491" Dst="-1" /><file name="Cooper_130620_053_tk_ar_4x6.jpg" server="jupiterupload.vcu.edu//www/www.facilitiesmanagement.vcu.edu/html/" local="3538674495" remote="3538674495" Dst="-1" /><file name="Stuart_130625_180_tk_ar_4x6.jpg" server="jupiterupload.vcu.edu//www/www.facilitiesmanagement.vcu.edu/html/" local="3538674492" remote="3538674492" Dst="-1" /><file name="GHOLSON_4x6.jpg" server="jupiterupload.vcu.edu//www/www.facilitiesmanagement.vcu.edu/html/" local="3538674490" remote="3538674490" Dst="-1" /><file name="Cosgrove_130620_078_tk_ar_4x6.jpg" server="jupiterupload.vcu.edu//www/www.facilitiesmanagement.vcu.edu/html/" local="3538674495" remote="3538674495" Dst="-1" /><file name="Lee_130712_142_tk_ar_4x6_old.jpg" server="jupiterupload.vcu.edu//www/www.facilitiesmanagement.vcu.edu/html/" local="3570108795" remote="3570108795" Dst="-1" /><file name="Grenoble_130712_029_tk_ar_4x6.jpg" server="jupiterupload.vcu.edu//www/www.facilitiesmanagement.vcu.edu/html/" local="3538674494" remote="3538674494" Dst="-1" /><file name="KIDD_4x6.jpg" server="jupiterupload.vcu.edu//www/www.facilitiesmanagement.vcu.edu/html/" local="3538674489" remote="3538674489" Dst="-1" /><file name="SUBRAMANIAN_4x6.jpg" server="jupiterupload.vcu.edu//www/www.facilitiesmanagement.vcu.edu/html/" local="3538674489" remote="3538674489" Dst="-1" /><file name="SMITHSON_4x6.jpg" server="jupiterupload.vcu.edu//www/www.facilitiesmanagement.vcu.edu/html/" local="3538674489" remote="3538674489" Dst="-1" /><file name="HARRISON_4x6.jpg" server="jupiterupload.vcu.edu//www/www.facilitiesmanagement.vcu.edu/html/" local="3538674489" remote="3538674489" Dst="-1" /><file name="Mannix_130712_078_tk_ar_4x6.jpg" server="jupiterupload.vcu.edu//www/www.facilitiesmanagement.vcu.edu/html/" local="3538674493" remote="3538674493" Dst="-1" /><file name="Martin_130712_100_tk_ar_4x6.jpg" server="jupiterupload.vcu.edu//www/www.facilitiesmanagement.vcu.edu/html/" local="3538674493" remote="3538674493" Dst="-1" /><file name="MARONEY_4x6.jpg" server="jupiterupload.vcu.edu//www/www.facilitiesmanagement.vcu.edu/html/" local="3538674489" remote="3538674489" Dst="-1" /><file name="STRISSEL_4x6.jpg" server="jupiterupload.vcu.edu//www/www.facilitiesmanagement.vcu.edu/html/" local="3538674489" remote="3538674489" Dst="-1" /><file name="Beaver_130625_116_tk_ar_4x6.jpg" server="jupiterupload.vcu.edu//www/www.facilitiesmanagement.vcu.edu/html/" local="3538674495" remote="3538674495" Dst="-1" /><file name="WYATT_4x6.jpg" server="jupiterupload.vcu.edu//www/www.facilitiesmanagement.vcu.edu/html/" local="3538674488" remote="3538674488" Dst="-1" /><file name="THRIFT_4x6.jpg" server="jupiterupload.vcu.edu//www/www.facilitiesmanagement.vcu.edu/html/" local="3538674488" remote="3538674488" Dst="-1" /><file name="Vtipil_130712_092_tk_ar_4x6.jpg" server="jupiterupload.vcu.edu//www/www.facilitiesmanagement.vcu.edu/html/" local="3538674492" remote="3538674492" Dst="-1" /><file name="Zumbrun_4x6.jpg" server="jupiterupload.vcu.edu//www/www.facilitiesmanagement.vcu.edu/html/" local="3538674487" remote="3538674487" Dst="-1" /><file name="Cox_130712_019_tk_ar_4x6.jpg" server="jupiterupload.vcu.edu//www/www.facilitiesmanagement.vcu.edu/html/" local="3538674495" remote="3538674495" Dst="-1" /><file name="Slutzah_130712_087_tk_ar_4x6_old.jpg" server="jupiterupload.vcu.edu//www/www.facilitiesmanagement.vcu.edu/html/" local="3538674488" remote="3538674488" Dst="-1" /><file name="TAYLOR_D_4x6.jpg" server="jupiterupload.vcu.edu//www/www.facilitiesmanagement.vcu.edu/html/" local="3538674488" remote="3538674488" Dst="-1" /><file name="Ware_130625_072_tk_ar_4x6.jpg" server="jupiterupload.vcu.edu//www/www.facilitiesmanagement.vcu.edu/html/" local="3538674492" remote="3538674492" Dst="-1" /><file name="Davidson_130620_023_tk_ar_4x6.jpg" server="jupiterupload.vcu.edu//www/www.facilitiesmanagement.vcu.edu/html/" local="3538674495" remote="3538674495" Dst="-1" /><file name="LONG_4x6.jpg" server="jupiterupload.vcu.edu//www/www.facilitiesmanagement.vcu.edu/html/" local="3538674491" remote="3538674491" Dst="-1" /><file name="MARTIN_4x6.jpg" server="jupiterupload.vcu.edu//www/www.facilitiesmanagement.vcu.edu/html/" local="3538674489" remote="3538674489" Dst="-1" /><file name="RiChard_130625_116_tk_ar_4x6.jpg" server="jupiterupload.vcu.edu//www/www.facilitiesmanagement.vcu.edu/html/" local="3538674491" remote="3538674491" Dst="-1" /><file name="PILSON_4x6.jpg" server="jupiterupload.vcu.edu//www/www.facilitiesmanagement.vcu.edu/html/" local="3538674492" remote="3538674492" Dst="-1" /><file name="BRITT_4x6.jpg" server="jupiterupload.vcu.edu//www/www.facilitiesmanagement.vcu.edu/html/" local="3538674490" remote="3538674490" Dst="-1" /></dwsync>